python_dtp/__init__.py
python_dtp/errors.py
python_dtp/local_db.py
python_dtp/monitor.py
python_dtp/tx.py
python_dtp/xa.py
python_dtp/xa_mysql.py
python_dtp/xa_postgresql.py
python_dtp-0.9.3.dist-info/METADATA
python_dtp-0.9.3.dist-info/WHEEL
python_dtp-0.9.3.dist-info/top_level.txt
python_dtp-0.9.3.dist-info/RECORD
