Metadata-Version: 2.1
Name: python-dtp
Version: 0.9.3
Summary: Python implementation of distributed transaction processing with MySQL, MySQLdb
Home-page: https://github.com/yueshuaijie/python_dtp
Author: yueshuaijie
Author-email: ysj@love.com
License: UNKNOWN
Platform: UNKNOWN
